<PAMDataset>
  <PAMRasterBand band="1">
    <Histograms>
      <HistItem>
        <HistMin>22.08672714233398</HistMin>
        <HistMax>27.81515884399414</HistMax>
        <BucketCount>256</BucketCount>
        <IncludeOutOfRange>1</IncludeOutOfRange>
        <Approximate>0</Approximate>
        <HistCounts>1|0|0|0|0|0|1|0|0|0|0|0|0|0|0|0|0|0|0|1|0|0|0|0|0|0|0|0|0|0|0|0|0|0|0|0|1|0|0|1|0|0|0|0|0|0|0|0|1|1|0|0|1|0|0|0|2|0|0|0|1|0|1|0|0|0|2|0|0|2|0|0|0|1|0|1|0|0|1|0|0|0|1|1|1|1|0|1|1|2|1|2|3|1|6|1|2|2|1|1|1|4|1|5|1|4|1|4|2|5|3|8|6|2|3|5|6|6|12|6|5|4|8|11|14|9|9|9|9|5|8|14|12|11|12|14|13|16|16|18|19|17|16|26|23|20|25|27|37|31|34|31|38|42|51|35|65|66|51|58|73|84|76|91|91|98|97|106|102|125|130|131|143|179|188|207|230|211|228|258|287|317|359|377|408|441|482|519|538|596|640|730|800|1060|1267|1618|1839|2158|2112|2298|2564|2682|2891|3141|3157|3409|3602|3659|3649|3745|3580|3760|3781|3961|4028|4033|4136|4082|4124|4073|3808|3568|3387|2987|2683|2331|1926|1654|1472|1245|1080|843|750|668|573|429|377|225|206|140|109|85|73|53|59|32|20|13|10|5|6|17|9|13|9|1</HistCounts>
      </HistItem>
    </Histograms>
    <Metadata>
      <MDI key="STATISTICS_COUNT">125678.000000</MDI>
      <MDI key="STATISTICS_COVARIANCES">0.1043030339464706</MDI>
      <MDI key="STATISTICS_EXCLUDEDVALUES"></MDI>
      <MDI key="STATISTICS_MAXIMUM">27.815158843994</MDI>
      <MDI key="STATISTICS_MEAN">26.814477629098</MDI>
      <MDI key="STATISTICS_MEDIAN">26.849188</MDI>
      <MDI key="STATISTICS_MINIMUM">22.086727142334</MDI>
      <MDI key="STATISTICS_SKIPFACTORX">1</MDI>
      <MDI key="STATISTICS_SKIPFACTORY">1</MDI>
      <MDI key="STATISTICS_STDDEV">0.32295980236938</MDI>
    </Metadata>
  </PAMRasterBand>
</PAMDataset>
